tess_flarefinder/Flare_model.py
tess_flarefinder/__init__.py
tess_flarefinder/data/model.dat
tess_flarefinder/flarefinder.py
tess_flarefinder/utils.py
tess_flarefinder/version.py
tess_flarefinder-0.5.0.dist-info/LICENSE
tess_flarefinder-0.5.0.dist-info/WHEEL
tess_flarefinder-0.5.0.dist-info/METADATA
tess_flarefinder-0.5.0.dist-info/RECORD
