Metadata-Version: 2.1
Name: tess-flarefinder
Version: 0.5.0
Summary: Find flares in TESS
Home-page: https://github.com/keyuxing/tess_flarefinder
License: MIT
Author: Keyu Xing
Author-email: kyxing@mail.bnu.edu.cn
Requires-Python: >=3.8,<3.11
Classifier: License :: OSI Approved :: MIT License
Classifier: Programming Language :: Python :: 3
Classifier: Programming Language :: Python :: 3.10
Classifier: Programming Language :: Python :: 3.8
Classifier: Programming Language :: Python :: 3.9
Requires-Dist: lightkurve (>=2.3,<3.0)
Requires-Dist: numba (>=0.55.2,<0.56.0)
Requires-Dist: retrying (>=1.3,<2.0)
Requires-Dist: tsfresh (>=0.19,<0.20)
Requires-Dist: wotan (>=1.10,<2.0)
Project-URL: Repository, https://github.com/keyuxing/tess_flarefinder
